{

    "bot_token"             : "bot_token",

    "secret_key"            : "secret_key",
    "standard_port"         : 12345,
    "multicast_port"        : 12345,

    "community_server_id"   : 123456789,
    "log_channel_id"        : 123456789,

    "db_name"               : "db_name",
    "db_user"               : "db_user",
    "db_password"           : "db_password",
    "db_host"               : "localhost",
    "db_port"               : 3306,

    "nodes"                 : [
        {
            "identifier": "MAIN",
            "ssl": false,
            "host": "localhost",
            "port": 2333,
            "password": "ll_password"
        }
    ],

    "topgg_token"           : "topgg_token"

}